setup.py
mozcommitbuilder/__init__.py
mozcommitbuilder/builder.py
mozcommitbuilder/mozInstall.py
mozcommitbuilder/trybuild.py
mozcommitbuilder/utils.py
mozcommitbuilder/ximport.py
mozcommitbuilder.egg-info/PKG-INFO
mozcommitbuilder.egg-info/SOURCES.txt
mozcommitbuilder.egg-info/dependency_links.txt
mozcommitbuilder.egg-info/entry_points.txt
mozcommitbuilder.egg-info/requires.txt
mozcommitbuilder.egg-info/top_level.txt