Metadata-Version: 1.1
Name: mozcommitbuilder
Version: 0.4.11
Summary: Regression finder using Mozilla central repo
Home-page: http://github.com/mozilla/mozcommitbuilder
Author: Sam Liu
Author-email: sam@ambushnetworks.com
License: MPL 1.1/GPL 2.0/LGPL 2.1
Platform: UNKNOWN
Classifier: Development Status :: 4 - Beta
Classifier: Intended Audience :: Developers
Classifier: Operating System :: OS Independent
